mingo/__init__.py
mingo/admin.py
mingo/apps.py
mingo/context_processors.py
mingo/forms.py
mingo/models.py
mingo/tests.py
mingo/urls.py
mingo/views.py
mingo/widgets.py
mingo/migrations/__init__.py
mingo/static/css/change-form.css
mingo/static/css/style.bundle.css
mingo/static/js/scripts.bundle.js
mingo/static/js/widgets.bundle.js
mingo/static/media/auth/404-error-dark.png
mingo/static/media/auth/404-error.png
mingo/static/media/auth/500-error-dark.png
mingo/static/media/auth/500-error.png
mingo/static/media/auth/505-error-dark.png
mingo/static/media/auth/505-error.png
mingo/static/media/auth/agency-dark.png
mingo/static/media/auth/agency.png
mingo/static/media/auth/bg1-dark.jpg
mingo/static/media/auth/bg1.jpg
mingo/static/media/auth/bg10-dark.jpeg
mingo/static/media/auth/bg10.jpeg
mingo/static/media/auth/bg11.png
mingo/static/media/auth/bg2-dark.jpg
mingo/static/media/auth/bg2.jpg
mingo/static/media/auth/bg3-dark.jpg
mingo/static/media/auth/bg3.jpg
mingo/static/media/auth/bg4-dark.jpg
mingo/static/media/auth/bg4.jpg
mingo/static/media/auth/bg5-dark.jpg
mingo/static/media/auth/bg5.jpg
mingo/static/media/auth/bg6-dark.jpg
mingo/static/media/auth/bg6.jpg
mingo/static/media/auth/bg7-dark.jpg
mingo/static/media/auth/bg7.jpg
mingo/static/media/auth/bg8-dark.jpg
mingo/static/media/auth/bg8.jpg
mingo/static/media/auth/bg9-dark.jpg
mingo/static/media/auth/bg9.jpg
mingo/static/media/auth/chart-graph-dark.png
mingo/static/media/auth/chart-graph.png
mingo/static/media/auth/membership-dark.png
mingo/static/media/auth/membership.png
mingo/static/media/auth/ok-dark.png
mingo/static/media/auth/ok.png
mingo/static/media/auth/please-verify-your-email-dark.png
mingo/static/media/auth/please-verify-your-email.png
mingo/static/media/auth/welcome-dark.png
mingo/static/media/auth/welcome.png
mingo/static/media/avatars/avatar.png
mingo/static/media/avatars/blank.png
mingo/static/media/logos/favicon.png
mingo/static/media/logos/logo-dark.png
mingo/static/media/logos/logo.png
django_mingo-1.0.1.dist-info/METADATA
django_mingo-1.0.1.dist-info/WHEEL
django_mingo-1.0.1.dist-info/top_level.txt
django_mingo-1.0.1.dist-info/RECORD
