Metadata-Version: 2.1
Name: django-mingo
Version: 1.0.1
Summary: Customize your django admin panel.
Author: Rupam Dhara
Author-email: thedevgenius83@gmail.com
License: MIT License
Classifier: Environment :: Web Environment
Classifier: Framework :: Django
Classifier: Programming Language :: Python :: 3.10
Classifier: License :: OSI Approved :: MIT License
Classifier: Operating System :: OS Independent
Requires-Dist: Django >=4.0
